[{"pk": 1, "model": "auth.permission", "fields": {"codename": "add_permission", "name": "Can add permission", "content_type": 1}}, {"pk": 2, "model": "auth.permission", "fields": {"codename": "change_permission", "name": "Can change permission", "content_type": 1}}, {"pk": 3, "model": "auth.permission", "fields": {"codename": "delete_permission", "name": "Can delete permission", "content_type": 1}}, {"pk": 4, "model": "auth.permission", "fields": {"codename": "add_group", "name": "Can add group", "content_type": 2}}, {"pk": 5, "model": "auth.permission", "fields": {"codename": "change_group", "name": "Can change group", "content_type": 2}}, {"pk": 6, "model": "auth.permission", "fields": {"codename": "delete_group", "name": "Can delete group", "content_type": 2}}, {"pk": 7, "model": "auth.permission", "fields": {"codename": "add_user", "name": "Can add user", "content_type": 3}}, {"pk": 8, "model": "auth.permission", "fields": {"codename": "change_user", "name": "Can change user", "content_type": 3}}, {"pk": 9, "model": "auth.permission", "fields": {"codename": "delete_user", "name": "Can delete user", "content_type": 3}}, {"pk": 10, "model": "auth.permission", "fields": {"codename": "add_contenttype", "name": "Can add content type", "content_type": 4}}, {"pk": 11, "model": "auth.permission", "fields": {"codename": "change_contenttype", "name": "Can change content type", "content_type": 4}}, {"pk": 12, "model": "auth.permission", "fields": {"codename": "delete_contenttype", "name": "Can delete content type", "content_type": 4}}, {"pk": 13, "model": "auth.permission", "fields": {"codename": "add_session", "name": "Can add session", "content_type": 5}}, {"pk": 14, "model": "auth.permission", "fields": {"codename": "change_session", "name": "Can change session", "content_type": 5}}, {"pk": 15, "model": "auth.permission", "fields": {"codename": "delete_session", "name": "Can delete session", "content_type": 5}}, {"pk": 16, "model": "auth.permission", "fields": {"codename": "add_site", "name": "Can add site", "content_type": 6}}, {"pk": 17, "model": "auth.permission", "fields": {"codename": "change_site", "name": "Can change site", "content_type": 6}}, {"pk": 18, "model": "auth.permission", "fields": {"codename": "delete_site", "name": "Can delete site", "content_type": 6}}, {"pk": 19, "model": "auth.permission", "fields": {"codename": "add_logentry", "name": "Can add log entry", "content_type": 7}}, {"pk": 20, "model": "auth.permission", "fields": {"codename": "change_logentry", "name": "Can change log entry", "content_type": 7}}, {"pk": 21, "model": "auth.permission", "fields": {"codename": "delete_logentry", "name": "Can delete log entry", "content_type": 7}}, {"pk": 22, "model": "auth.permission", "fields": {"codename": "add_activity", "name": "Can add activity", "content_type": 8}}, {"pk": 23, "model": "auth.permission", "fields": {"codename": "change_activity", "name": "Can change activity", "content_type": 8}}, {"pk": 24, "model": "auth.permission", "fields": {"codename": "delete_activity", "name": "Can delete activity", "content_type": 8}}, {"pk": 25, "model": "auth.permission", "fields": {"codename": "add_item", "name": "Can add item", "content_type": 9}}, {"pk": 26, "model": "auth.permission", "fields": {"codename": "change_item", "name": "Can change item", "content_type": 9}}, {"pk": 27, "model": "auth.permission", "fields": {"codename": "delete_item", "name": "Can delete item", "content_type": 9}}, {"pk": 28, "model": "auth.permission", "fields": {"codename": "add_category", "name": "Can add category", "content_type": 10}}, {"pk": 29, "model": "auth.permission", "fields": {"codename": "change_category", "name": "Can change category", "content_type": 10}}, {"pk": 30, "model": "auth.permission", "fields": {"codename": "delete_category", "name": "Can delete category", "content_type": 10}}, {"pk": 1, "model": "auth.user", "fields": {"username": "admin", "first_name": "", "last_name": "", "is_active": true, "is_superuser": true, "is_staff": true, "last_login": "2013-07-23T07:57:22.415Z", "groups": [], "user_permissions": [], "password": "pbkdf2_sha256$10000$FKFcTtESItmQ$NBvto5dc5X04DfhjO8Wq3fjPl1ioow8rrfUoEYENCl0=", "email": "admin@postech.ac.kr", "date_joined": "2013-07-23T07:57:22.415Z"}}, {"pk": 2, "model": "auth.user", "fields": {"username": "user1", "first_name": "User", "last_name": "One", "is_active": true, "is_superuser": false, "is_staff": false, "last_login": "2013-07-25T01:32:18.707Z", "groups": [], "user_permissions": [], "password": "", "email": "user1@gmail.com", "date_joined": "2013-07-25T01:32:18.707Z"}}, {"pk": 3, "model": "auth.user", "fields": {"username": "user2", "first_name": "User", "last_name": "Two", "is_active": true, "is_superuser": false, "is_staff": false, "last_login": "2013-07-25T01:33:02.831Z", "groups": [], "user_permissions": [], "password": "", "email": "user2@gmail.com", "date_joined": "2013-07-25T01:33:02.831Z"}}, {"pk": 4, "model": "auth.user", "fields": {"username": "user3", "first_name": "User", "last_name": "Three", "is_active": true, "is_superuser": false, "is_staff": false, "last_login": "2013-07-25T01:33:23.314Z", "groups": [], "user_permissions": [], "password": "", "email": "user3@gmail.com", "date_joined": "2013-07-25T01:33:23.314Z"}}, {"pk": 5, "model": "auth.user", "fields": {"username": "user5", "first_name": "User", "last_name": "Five", "is_active": true, "is_superuser": false, "is_staff": false, "last_login": "2013-07-25T01:37:34.101Z", "groups": [], "user_permissions": [], "password": "", "email": "user5@gmail.com", "date_joined": "2013-07-25T01:37:34.101Z"}}]